dimae/__init__.py
dimae/autoencoders/__init__.py
dimae/autoencoders/autoencoder.py
dimae/autoencoders/main.py
dimae/autoencoders/utils.py
dimae-0.1.4.dist-info/LICENSE
dimae-0.1.4.dist-info/METADATA
dimae-0.1.4.dist-info/WHEEL
dimae-0.1.4.dist-info/top_level.txt
dimae-0.1.4.dist-info/RECORD
