Metadata-Version: 2.1
Name: dimae
Version: 0.1.4
Summary: Dimensionality Autoencoder
Home-page: https://github.com/SynStratos/dim_ae
Author: SynStratos
Author-email: synstratos.dev@gmail.com
License: UNKNOWN
Platform: UNKNOWN
Classifier: Programming Language :: Python :: 3
Classifier: License :: OSI Approved :: MIT License
Classifier: Operating System :: OS Independent
Requires-Python: >=3.6
Requires-Dist: numpy
Requires-Dist: tensorflow
Requires-Dist: scikit-learn
